svfs3/__init__.py
svfs3/svfs.py
svfs3-3.0.0.dist-info/METADATA
svfs3-3.0.0.dist-info/WHEEL
svfs3-3.0.0.dist-info/licenses/LICENSE.txt
svfs3-3.0.0.dist-info/RECORD
