Metadata-Version: 2.4
Name: svfs3
Version: 3.0.0
Summary: Multi-purpose virtual file system inside single file (ported to Python 3)
Project-URL: Homepage, https://github.com/ospoco/SVFS3
Project-URL: Repository, https://github.com/ospoco/SVFS3.git
Author-email: Andrew Stolberg <andrewstolberg@gmail.com>, Van Lindberg <van.lindberg@gmail.com>
Maintainer-email: Van Lindberg <van.lindberg@gmail.com>
License-Expression: GPL-3.0
License-File: LICENSE.txt
Keywords: archiving,file-system,filesystem
Classifier: Development Status :: 4 - Beta
Classifier: Environment :: Other Environment
Classifier: Intended Audience :: Developers
Classifier: Operating System :: OS Independent
Classifier: Programming Language :: Python :: 3
Classifier: Programming Language :: Python :: 3.9
Classifier: Programming Language :: Python :: 3.10
Classifier: Programming Language :: Python :: 3.11
Classifier: Programming Language :: Python :: 3.12
Classifier: Programming Language :: Python :: 3.13
Classifier: Topic :: Software Development :: Libraries :: Python Modules
Classifier: Topic :: System :: Filesystems
Requires-Python: >=3.9
Requires-Dist: cryptography>=44.0.1
